Workbook

Sheet 价卡
A1: 国家 | B1: 地区 | C1: 渠道 | D1: 币种 | E1: 跨境物流成本 | H1: 买家支付运费 | I1: 卖家支付运费=跨境物流成本+买家支付运费
E2: 起重重量 (g) | F2: 起重价格 | G2: 续重价格（每10g） | I2: 起重重量 (g) | J2: 起重价格 | K2: 续重价格（每10g）
A3: 泰国 | B3: Zone A | C3: Standard | D3: THB | E3: 10 | F3: 1 | G3: 1 | H3: 23 | I3: 10 | J3: =H3+F3 -> 24 | K3: =G3 -> 1
B4: Zone B | C4: Standard | D4: THB | E4: 10 | F4: 1 | G4: 1 | H4: 36 | I4: 10 | J4: =H4+F4 -> 37 | K4: =G4 -> 1
B5: Zone C | E5: 10 | F5: 1 | G5: 1 | H5: 79 | I5: 10 | J5: 80 | K5: =G5 -> 1
A6: 越南 | B6: Zone A | C6: Economy | D6: VND | E6: 10 | F6: 10900 | G6: 900 | H6: 15000 | I6: 10 | J6: 25900 | K6: =G6 -> 900
B7: Zone B | E7: 10 | F7: 10900 | G7: 900 | H7: 17000 | I7: 10 | J7: 27900 | K7: =G7 -> 900
B8: Zone C | E8: 10 | F8: 10900 | G8: 900 | H8: 17000 | I8: 10 | J8: 27900 | K8: =G8 -> 900
B9: Zone D | C9: Standard | D9: THB | E9: 10 | F9: 10900 | G9: 900 | H9: 30000 | I9: 10 | J9: 40900 | K9: =G9 -> 900
A10: 马来西亚 | B10: 西马 | C10: Standard | D10: MYR | E10: 10 | F10: 0.15 | G10: 0.15 | H10: 4.9 | I10: 10 | J10: =H10+F10 -> 5.05 | K10: =G10 -> 0.15
B11: 东马 | C11: Standard | D11: MYR | E11: 10 | F11: 0.15 | G11: 0.15 | H11: 10 | I11: 10 | J11: =H11+F11 -> 10.15 | K11: =G11 -> 0.15
A12: 菲律宾 | B12: 马尼拉 | C12: Standard | D12: PHP | E12: 10 | F12: 10.5 | G12: 4.5 | H12: 40 | I12: 10 | J12: =H12+F12 -> 50.5 | K12: =G12 -> 4.5
B13: 其他区 | C13: Standard | D13: PHP | E13: 10 | F13: 10.5 | G13: 4.5 | H13: 60 | I13: 10 | J13: =H13+F13 -> 70.5 | K13: =G13 -> 4.5
A14: 新加坡 | B14: 全境 | C14: Standard | D14: SGD | E14: 40 | F14: 0.98 | G14: 0.15 | H14: 0 | I14: 40 | J14: =F14+H14 -> 0.98 | K14: 0.15
A16: 备注 | B16: 计费重为实重

Sheet 跨境物流成本计算工具
B2: 如何使用跨境物流成本计算工具：
B3: 1. 将产品ID，产品重量填入下方“商品信息”一栏中 2. 相应市场的跨境物流成本将自动展示在右侧表格 3. 请注意：此工具计算结果仅做参考，实际订单可能会出现一单多件或者包裹重量不符的情况，因此会有差异。
B5: 商品信息 | D5: 跨境物流成本（当地货币）
B6: SKU ID | C6: 重量（克） | D6: 泰国 | E6: 越南 | F6: 马来西亚 | G6: 菲律宾 | H6: 新加坡
D7: THB | E7: VND | F7: MYR | G7: PHP | H7: SGD
B8: AAAA | C8: 300 | D8: {=IFERROR(VLOOKUP(ROUNDUP($C8:$C995,-1),泰国!$B$11:$C$2010,2,FALSE),"")} -> 30 | E8: {=IFERROR(VLOOKUP(ROUNDUP($C8:$C995,-1),越南!$B$11:$C$3010,2,FALSE),"")} -> 37000 | F8: {=IFERROR(VLOOKUP(ROUNDUP($C8:$C995,-1),马来西亚!$B$11:$C$3010,2,FALSE),"")} -> 4.5 | G8: {=IFERROR(VLOOKUP(ROUNDUP($C8:$C995,-1),菲律宾!$B$11:$C$3010,2,FALSE),"")} -> 141 | H8: {=IFERROR(VLOOKUP(ROUNDUP($C8:$C995,-1),新加坡!$B$10:$C$3009,2,FALSE),"")} -> 4.88
B9: BBBB | C9: 500 | D9: 50 | E9: 55000 | F9: 7.5 | G9: 231 | H9: 7.88
B10: CCCC | C10: 1121 | D10: 113 | E10: 111700 | F10: 16.95 | G10: 514.5 | H10: 17.33

Sheet 菲律宾
B2: 生效日期 | C2: 44676
B3: 货币 | C3: PHP
B6: 跨境物流成本 | E6: 当地派送物流成本 (买家下单时支付运费) | H6: 总物流成本
B7: *按照包裹实重计费 | E7: *按照渠道计费 | H7: *跨境物流成本 + 当地派送物流成本
B9: 重量（克） | C9: 全境 | E9: Standard渠道 | H9: 重量（克） | I9: Standard渠道
E10: 马尼拉 | F10: 其他区 | I10: 马尼拉 | J10: 其他区
B11: 10 | C11: =价卡!F12 -> 10.5 | E11: 40 | F11: 60 | H11: 10 | I11: =C11+$E$11 -> 50.5 | J11: =C11+$F$11 -> 70.5
B12: 20 | C12: =C11+4.5 -> 15 | H12: 20 | I12: =C12+$E$11 -> 55 | J12: =C12+$F$11 -> 75
B13: 30 | C13: =C12+4.5 -> 19.5 | H13: 30 | I13: =C13+$E$11 -> 59.5 | J13: =C13+$F$11 -> 79.5
B14: 40 | C14: =C13+4.5 -> 24 | H14: 40 | I14: =C14+$E$11 -> 64 | J14: =C14+$F$11 -> 84
B15: 50 | C15: =C14+4.5 -> 28.5 | H15: 50 | I15: =C15+$E$11 -> 68.5 | J15: =C15+$F$11 -> 88.5
B16: 60 | C16: =C15+4.5 -> 33 | H16: 60 | I16: =C16+$E$11 -> 73 | J16: =C16+$F$11 -> 93
B17: 70 | C17: =C16+4.5 -> 37.5 | H17: 70 | I17: =C17+$E$11 -> 77.5 | J17: =C17+$F$11 -> 97.5
B18: 80 | C18: =C17+4.5 -> 42 | H18: 80 | I18: =C18+$E$11 -> 82 | J18: =C18+$F$11 -> 102
B19: 90 | C19: =C18+4.5 -> 46.5 | H19: 90 | I19: =C19+$E$11 -> 86.5 | J19: =C19+$F$11 -> 106.5
B20: 100 | C20: =C19+4.5 -> 51 | H20: 100 | I20: =C20+$E$11 -> 91 | J20: =C20+$F$11 -> 111
B21: 110 | C21: =C20+4.5 -> 55.5 | H21: 110 | I21: =C21+$E$11 -> 95.5 | J21: =C21+$F$11 -> 115.5
B22: 120 | C22: =C21+4.5 -> 60 | H22: 120 | I22: =C22+$E$11 -> 100 | J22: =C22+$F$11 -> 120
B23: 130 | C23: =C22+4.5 -> 64.5 | H23: 130 | I23: =C23+$E$11 -> 104.5 | J23: =C23+$F$11 -> 124.5
... B3010: 30000 | C3010: =C3009+4.5 -> 13506 | H3010: 30000 | I3010: =C3010+$E$11 -> 13546 | J3010: =C3010+$F$11 -> 13566

Sheet 马来西亚
B2: 生效日期 | C2: 45397
B3: 货币 | C3: MYR
B6: 跨境物流成本 | E6: 当地派送物流成本 (买家下单时支付运费) | H6: 总物流成本
B7: *按照包裹实重计费 | E7: *按照渠道计费 | H7: *跨境物流成本 + 当地派送物流成本
B9: 重量（克） | C9: 全境 | E9: Standard渠道 | H9: 重量（克） | I9: Standard渠道
E10: 西马 | F10: 东马 | I10: 西马 | J10: 东马
B11: 10 | C11: 0.15 | E11: 4.9 | F11: 10 | H11: 10 | I11: =C11+$E$11 -> 5.05 | J11: =C11+$F$11 -> 10.15
B12: 20 | C12: 0.3 | H12: 20 | I12: =C12+$E$11 -> 5.2 | J12: =C12+$F$11 -> 10.3
B13: 30 | C13: 0.45 | H13: 30 | I13: =C13+$E$11 -> 5.35 | J13: =C13+$F$11 -> 10.45
B14: 40 | C14: 0.6 | H14: 40 | I14: =C14+$E$11 -> 5.5 | J14: =C14+$F$11 -> 10.6
B15: 50 | C15: 0.75 | H15: 50 | I15: =C15+$E$11 -> 5.65 | J15: =C15+$F$11 -> 10.75
B16: 60 | C16: 0.9 | H16: 60 | I16: =C16+$E$11 -> 5.8 | J16: =C16+$F$11 -> 10.9
B17: 70 | C17: 1.05 | H17: 70 | I17: =C17+$E$11 -> 5.95 | J17: =C17+$F$11 -> 11.05
B18: 80 | C18: 1.2 | H18: 80 | I18: =C18+$E$11 -> 6.1 | J18: =C18+$F$11 -> 11.2
B19: 90 | C19: 1.35 | H19: 90 | I19: =C19+$E$11 -> 6.25 | J19: =C19+$F$11 -> 11.35
B20: 100 | C20: 1.5 | H20: 100 | I20: =C20+$E$11 -> 6.4 | J20: =C20+$F$11 -> 11.5
B21: 110 | C21: 1.65 | H21: 110 | I21: =C21+$E$11 -> 6.55 | J21: =C21+$F$11 -> 11.65
B22: 120 | C22: 1.8 | H22: 120 | I22: =C22+$E$11 -> 6.7 | J22: =C22+$F$11 -> 11.8
B23: 130 | C23: 1.95 | H23: 130 | I23: =C23+$E$11 -> 6.85 | J23: =C23+$F$11 -> 11.95
... B3010: 30000 | C3010: 450 | H3010: 30000 | I3010: =C3010+$E$11 -> 454.9 | J3010: =C3010+$F$11 -> 460

Sheet 泰国
B2: 生效日期 | C2: 45107
B3: 货币 | C3: THB
B6: 跨境物流成本 | E6: 当地派送物流成本 (买家下单时支付运费) | I6: 总物流成本
B7: *按照包裹实重计费 | E7: *按照渠道计费 | I7: *跨境物流成本 + 当地派送物流成本
B9: 重量（克） | C9: 全境 | E9: Standard渠道 | I9: 重量（克） | J9: Standard渠道
E10: Zone A | F10: Zone B | G10: Zone C | J10: Zone A | K10: Zone B | L10: Zone C
B11: 10 | C11: 1 | E11: 23 | F11: 36 | G11: 79 | I11: 10 | J11: =$C11+E$11 -> 24 | K11: =$C11+F$11 -> 37 | L11: =$C11+G$11 -> 80
B12: 20 | C12: 2 | I12: 20 | J12: =$C12+E$11 -> 25 | K12: =$C12+F$11 -> 38 | L12: =$C12+G$11 -> 81
B13: 30 | C13: 3 | I13: 30 | J13: =$C13+E$11 -> 26 | K13: =$C13+F$11 -> 39 | L13: =$C13+G$11 -> 82
B14: 40 | C14: 4 | I14: 40 | J14: =$C14+E$11 -> 27 | K14: =$C14+F$11 -> 40 | L14: =$C14+G$11 -> 83
B15: 50 | C15: 5 | I15: 50 | J15: =$C15+E$11 -> 28 | K15: =$C15+F$11 -> 41 | L15: =$C15+G$11 -> 84
B16: 60 | C16: 6 | I16: 60 | J16: =$C16+E$11 -> 29 | K16: =$C16+F$11 -> 42 | L16: =$C16+G$11 -> 85
B17: 70 | C17: 7 | I17: 70 | J17: =$C17+E$11 -> 30 | K17: =$C17+F$11 -> 43 | L17: =$C17+G$11 -> 86
B18: 80 | C18: 8 | I18: 80 | J18: =$C18+E$11 -> 31 | K18: =$C18+F$11 -> 44 | L18: =$C18+G$11 -> 87
B19: 90 | C19: 9 | I19: 90 | J19: =$C19+E$11 -> 32 | K19: =$C19+F$11 -> 45 | L19: =$C19+G$11 -> 88
B20: 100 | C20: 10 | I20: 100 | J20: =$C20+E$11 -> 33 | K20: =$C20+F$11 -> 46 | L20: =$C20+G$11 -> 89
B21: 110 | C21: 11 | I21: 110 | J21: =$C21+E$11 -> 34 | K21: =$C21+F$11 -> 47 | L21: =$C21+G$11 -> 90
B22: 120 | C22: 12 | I22: 120 | J22: =$C22+E$11 -> 35 | K22: =$C22+F$11 -> 48 | L22: =$C22+G$11 -> 91
B23: 130 | C23: 13 | I23: 130 | J23: =$C23+E$11 -> 36 | K23: =$C23+F$11 -> 49 | L23: =$C23+G$11 -> 92
... B2010: 20000 | C2010: 2000 | I2010: 20000 | J2010: =$C2010+E$11 -> 2023 | K2010: =$C2010+F$11 -> 2036 | L2010: =$C2010+G$11 -> 2079

Sheet 越南
B2: 生效日期 | C2: 45930
B3: 货币 | C3: VND
B6: 跨境物流成本 | E6: 当地派送物流成本 (买家下单时支付运费) | J6: 总物流成本
B7: *按照包裹实重计费 | E7: *按照渠道计费 | J7: *跨境物流成本 + 当地派送物流成本
B9: 重量（克） | C9: 全境 | E9: Economy渠道 | J9: 重量（克） | K9: Economy渠道
E10: Zone A | F10: Zone B | G10: Zone C | H10: Zone D | K10: Zone A | L10: Zone B | M10: Zone C | N10: Zone D
B11: 10 | C11: =IF(B11<=价卡!$E$6,价卡!$F$6,价卡!$F$6+价卡!$G$6*(B11-价卡!$E$6)/10) -> 10900 | E11: 15000 | F11: 17000 | G11: 17000 | H11: 30000 | J11: 10 | K11: =C11+$E$11 -> 25900 | L11: =C11+$F$11 -> 27900 | M11: =C11+$G$11 -> 27900 | N11: =C11+$H$11 -> 40900
B12: 20 | C12: =IF(B12<=价卡!$E$6,价卡!$F$6,价卡!$F$6+价卡!$G$6*(B12-价卡!$E$6)/10) -> 11800 | J12: 20 | K12: =C12+$E$11 -> 26800 | L12: =C12+$F$11 -> 28800 | M12: =C12+$G$11 -> 28800 | N12: =C12+$H$11 -> 41800
B13: 30 | C13: =IF(B13<=价卡!$E$6,价卡!$F$6,价卡!$F$6+价卡!$G$6*(B13-价卡!$E$6)/10) -> 12700 | J13: 30 | K13: =C13+$E$11 -> 27700 | L13: =C13+$F$11 -> 29700 | M13: =C13+$G$11 -> 29700 | N13: =C13+$H$11 -> 42700
B14: 40 | C14: =IF(B14<=价卡!$E$6,价卡!$F$6,价卡!$F$6+价卡!$G$6*(B14-价卡!$E$6)/10) -> 13600 | J14: 40 | K14: =C14+$E$11 -> 28600 | L14: =C14+$F$11 -> 30600 | M14: =C14+$G$11 -> 30600 | N14: =C14+$H$11 -> 43600
B15: 50 | C15: =IF(B15<=价卡!$E$6,价卡!$F$6,价卡!$F$6+价卡!$G$6*(B15-价卡!$E$6)/10) -> 14500 | J15: 50 | K15: =C15+$E$11 -> 29500 | L15: =C15+$F$11 -> 31500 | M15: =C15+$G$11 -> 31500 | N15: =C15+$H$11 -> 44500
B16: 60 | C16: =IF(B16<=价卡!$E$6,价卡!$F$6,价卡!$F$6+价卡!$G$6*(B16-价卡!$E$6)/10) -> 15400 | J16: 60 | K16: =C16+$E$11 -> 30400 | L16: =C16+$F$11 -> 32400 | M16: =C16+$G$11 -> 32400 | N16: =C16+$H$11 -> 45400
B17: 70 | C17: =IF(B17<=价卡!$E$6,价卡!$F$6,价卡!$F$6+价卡!$G$6*(B17-价卡!$E$6)/10) -> 16300 | J17: 70 | K17: =C17+$E$11 -> 31300 | L17: =C17+$F$11 -> 33300 | M17: =C17+$G$11 -> 33300 | N17: =C17+$H$11 -> 46300
B18: 80 | C18: =IF(B18<=价卡!$E$6,价卡!$F$6,价卡!$F$6+价卡!$G$6*(B18-价卡!$E$6)/10) -> 17200 | J18: 80 | K18: =C18+$E$11 -> 32200 | L18: =C18+$F$11 -> 34200 | M18: =C18+$G$11 -> 34200 | N18: =C18+$H$11 -> 47200
B19: 90 | C19: =IF(B19<=价卡!$E$6,价卡!$F$6,价卡!$F$6+价卡!$G$6*(B19-价卡!$E$6)/10) -> 18100 | J19: 90 | K19: =C19+$E$11 -> 33100 | L19: =C19+$F$11 -> 35100 | M19: =C19+$G$11 -> 35100 | N19: =C19+$H$11 -> 48100
B20: 100 | C20: =IF(B20<=价卡!$E$6,价卡!$F$6,价卡!$F$6+价卡!$G$6*(B20-价卡!$E$6)/10) -> 19000 | J20: 100 | K20: =C20+$E$11 -> 34000 | L20: =C20+$F$11 -> 36000 | M20: =C20+$G$11 -> 36000 | N20: =C20+$H$11 -> 49000
B21: 110 | C21: =IF(B21<=价卡!$E$6,价卡!$F$6,价卡!$F$6+价卡!$G$6*(B21-价卡!$E$6)/10) -> 19900 | J21: 110 | K21: =C21+$E$11 -> 34900 | L21: =C21+$F$11 -> 36900 | M21: =C21+$G$11 -> 36900 | N21: =C21+$H$11 -> 49900
B22: 120 | C22: =IF(B22<=价卡!$E$6,价卡!$F$6,价卡!$F$6+价卡!$G$6*(B22-价卡!$E$6)/10) -> 20800 | J22: 120 | K22: =C22+$E$11 -> 35800 | L22: =C22+$F$11 -> 37800 | M22: =C22+$G$11 -> 37800 | N22: =C22+$H$11 -> 50800
B23: 130 | C23: =IF(B23<=价卡!$E$6,价卡!$F$6,价卡!$F$6+价卡!$G$6*(B23-价卡!$E$6)/10) -> 21700 | J23: 130 | K23: =C23+$E$11 -> 36700 | L23: =C23+$F$11 -> 38700 | M23: =C23+$G$11 -> 38700 | N23: =C23+$H$11 -> 51700
... B3010: 30000 | C3010: =IF(B3010<=价卡!$E$6,价卡!$F$6,价卡!$F$6+价卡!$G$6*(B3010-价卡!$E$6)/10) -> 2710000 | J3010: 30000 | K3010: =C3010+$E$11 -> 2725000 | L3010: =C3010+$F$11 -> 2727000 | M3010: =C3010+$G$11 -> 2727000 | N3010: =C3010+$H$11 -> 2740000

Sheet 新加坡
B2: 生效日期 | C2: 45728
B3: 货币 | C3: SGD
B6: 跨境物流成本（藏价） | E6: 当地派送物流成本 (买家下单时支付运费) | G6: 总物流成本
B7: *按照包裹实重计费 | E7: *按照渠道计费 | G7: *跨境物流成本 + 当地派送物流成本
B9: 重量（克） | C9: 全境 | E9: Standard渠道 | G9: 重量（克） | H9: Standard渠道
B10: 10 | C10: =IF(B10<=价卡!$E$14,价卡!$F$14,价卡!$F$14+价卡!$G$14*(B10-价卡!$E$14)/10) -> 0.98 | E10: =价卡!H14 -> 0 | G10: 10 | H10: =C10+$E$10 -> 0.98
B11: 20 | C11: =IF(B11<=价卡!$E$14,价卡!$F$14,价卡!$F$14+价卡!$G$14*(B11-价卡!$E$14)/10) -> 0.98 | G11: 20 | H11: =C11+$E$10 -> 0.98
B12: 30 | C12: =IF(B12<=价卡!$E$14,价卡!$F$14,价卡!$F$14+价卡!$G$14*(B12-价卡!$E$14)/10) -> 0.98 | G12: 30 | H12: =C12+$E$10 -> 0.98
B13: 40 | C13: =IF(B13<=价卡!$E$14,价卡!$F$14,价卡!$F$14+价卡!$G$14*(B13-价卡!$E$14)/10) -> 0.98 | G13: 40 | H13: =C13+$E$10 -> 0.98
B14: 50 | C14: =IF(B14<=价卡!$E$14,价卡!$F$14,价卡!$F$14+价卡!$G$14*(B14-价卡!$E$14)/10) -> 1.13 | G14: 50 | H14: =C14+$E$10 -> 1.13
B15: 60 | C15: =IF(B15<=价卡!$E$14,价卡!$F$14,价卡!$F$14+价卡!$G$14*(B15-价卡!$E$14)/10) -> 1.28 | G15: 60 | H15: =C15+$E$10 -> 1.28
B16: 70 | C16: =IF(B16<=价卡!$E$14,价卡!$F$14,价卡!$F$14+价卡!$G$14*(B16-价卡!$E$14)/10) -> 1.43 | G16: 70 | H16: =C16+$E$10 -> 1.43
B17: 80 | C17: =IF(B17<=价卡!$E$14,价卡!$F$14,价卡!$F$14+价卡!$G$14*(B17-价卡!$E$14)/10) -> 1.58 | G17: 80 | H17: =C17+$E$10 -> 1.58
B18: 90 | C18: =IF(B18<=价卡!$E$14,价卡!$F$14,价卡!$F$14+价卡!$G$14*(B18-价卡!$E$14)/10) -> 1.73 | G18: 90 | H18: =C18+$E$10 -> 1.73
B19: 100 | C19: =IF(B19<=价卡!$E$14,价卡!$F$14,价卡!$F$14+价卡!$G$14*(B19-价卡!$E$14)/10) -> 1.88 | G19: 100 | H19: =C19+$E$10 -> 1.88
B20: 110 | C20: =IF(B20<=价卡!$E$14,价卡!$F$14,价卡!$F$14+价卡!$G$14*(B20-价卡!$E$14)/10) -> 2.03 | G20: 110 | H20: =C20+$E$10 -> 2.03
B21: 120 | C21: =IF(B21<=价卡!$E$14,价卡!$F$14,价卡!$F$14+价卡!$G$14*(B21-价卡!$E$14)/10) -> 2.18 | G21: 120 | H21: =C21+$E$10 -> 2.18
B22: 130 | C22: =IF(B22<=价卡!$E$14,价卡!$F$14,价卡!$F$14+价卡!$G$14*(B22-价卡!$E$14)/10) -> 2.33 | G22: 130 | H22: =C22+$E$10 -> 2.33
... B3009: 30000 | C3009: =IF(B3009<=价卡!$E$14,价卡!$F$14,价卡!$F$14+价卡!$G$14*(B3009-价卡!$E$14)/10) -> 450.38 | G3009: 30000 | H3009: =C3009+$E$10 -> 450.38

Sheet 区域划分
A1: 国家 | B1: 省份 | C1: 区域
A2: 菲律宾 | B2: Metro Manila | C2: 大马尼拉区
A3: 菲律宾 | B3: ARMM | C3: 其他
A4: 菲律宾 | B4: Bicol | C4: 其他
A5: 菲律宾 | B5: Cagayan Valley | C5: 其他
A6: 菲律宾 | B6: Calabarzon | C6: 其他
A7: 菲律宾 | B7: Caraga | C7: 其他
A8: 菲律宾 | B8: Central Luzon | C8: 其他
A9: 菲律宾 | B9: Central Visayas | C9: 其他
A10: 菲律宾 | B10: Cordillera | C10: 其他
A11: 菲律宾 | B11: Davao | C11: 其他
A12: 菲律宾 | B12: Eastern Visayas | C12: 其他
... A3434: 越南 | B3434: Xã Trường Lâm | C3434: Zone B&C
